chibihash-0.2.0.dist-info/METADATA
chibihash-0.2.0.dist-info/WHEEL
chibihash-0.2.0.dist-info/licenses/LICENSE
chibihash/py.typed
chibihash/_core.pyi
chibihash/__init__.py
chibihash/_core.pyd
chibihash-0.2.0.dist-info/RECORD
