Metadata-Version: 2.3
Name: chibihash
Version: 0.2.0
Classifier: Development Status :: 4 - Beta
Classifier: Intended Audience :: Developers
Classifier: License :: OSI Approved :: Apache Software License
Classifier: Programming Language :: Python :: 3
Classifier: Programming Language :: Python :: 3.9
Classifier: Programming Language :: Python :: 3.10
Classifier: Programming Language :: Python :: 3.11
Classifier: Programming Language :: Python :: 3.12
Classifier: Topic :: Software Development :: Libraries :: Python Modules
License-File: LICENSE
Summary: Chibihash implementation in Rust/Python
Keywords: hash,chibihash
Home-Page: https://github.com/jimexist/chibihash
Author-email: Jiayu Liu <jiayu@hey.com>
License: Apache-2.0
Requires-Python: >=3.9
Project-URL: homepage, https://github.com/jimexist/chibihash
Project-URL: issues, https://github.com/jimexist/chibihash/issues
